{
  "main": {
    "id": "e80fbc85270f849c",
    "type": "split",
    "children": [
      {
        "id": "f25a1a8b10bf10d3",
        "type": "tabs",
        "children": [
          {
            "id": "bfc341ff9cb80625",
            "type": "leaf",
            "state": {
              "type": "markdown",
              "state": {
                "file": "index.md",
                "mode": "source",
                "source": false
              }
            }
          },
          {
            "id": "00393ee35e9f6bdc",
            "type": "leaf",
            "state": {
              "type": "markdown",
              "state": {
                "file": "CalenderNotes/TEST PROGRESS.md",
                "mode": "source",
                "source": false
              }
            }
          },
          {
            "id": "2949ed3f81e64650",
            "type": "leaf",
            "state": {
              "type": "markdown",
              "state": {
                "file": "CalenderNotes/TOC/2023-10-03 Test ID - 36 Toc Test - 1 - 2023.md",
                "mode": "source",
                "source": false
              }
            }
          },
          {
            "id": "815b1f3778b8b01d",
            "type": "leaf",
            "state": {
              "type": "markdown",
              "state": {
                "file": "DialyStuff/2023-10-05.md",
                "mode": "source",
                "source": false
              }
            }
          }
        ],
        "currentTab": 2
      }
    ],
    "direction": "vertical"
  },
  "left": {
    "id": "0a9ce58cff7e5b86",
    "type": "split",
    "children": [
      {
        "id": "c3e2ce9e99e41b3a",
        "type": "tabs",
        "children": [
          {
            "id": "5b301f141e47d7da",
            "type": "leaf",
            "state": {
              "type": "file-explorer",
              "state": {
                "sortOrder": "alphabetical"
              }
            }
          },
          {
            "id": "f05219de2c216c2d",
            "type": "leaf",
            "state": {
              "type": "search",
              "state": {
                "query": "",
                "matchingCase": false,
                "explainSearch": false,
                "collapseAll": false,
                "extraContext": true,
                "sortOrder": "alphabetical"
              }
            }
          },
          {
            "id": "e41ff63964e51d38",
            "type": "leaf",
            "state": {
              "type": "bookmarks",
              "state": {}
            }
          },
          {
            "id": "d46a52c34033a3d8",
            "type": "leaf",
            "state": {
              "type": "trash-explorer",
              "state": {}
            }
          },
          {
            "id": "b124b1ce60556a81",
            "type": "leaf",
            "state": {
              "type": "mk-file-view",
              "state": {}
            }
          }
        ]
      }
    ],
    "direction": "horizontal",
    "width": 272.5043640136719
  },
  "right": {
    "id": "c41539313e85ef1f",
    "type": "split",
    "children": [
      {
        "id": "e2c33a18752ec2d0",
        "type": "tabs",
        "children": [
          {
            "id": "7ec0733dda91710c",
            "type": "leaf",
            "state": {
              "type": "backlink",
              "state": {
                "file": "CalenderNotes/TOC/2023-10-03 Test ID - 36 Toc Test - 1 - 2023.md",
                "collapseAll": false,
                "extraContext": false,
                "sortOrder": "alphabetical",
                "showSearch": false,
                "searchQuery": "",
                "backlinkCollapsed": false,
                "unlinkedCollapsed": true
              }
            }
          },
          {
            "id": "65b2c4a5b14b47db",
            "type": "leaf",
            "state": {
              "type": "outgoing-link",
              "state": {
                "file": "CalenderNotes/TOC/2023-10-03 Test ID - 36 Toc Test - 1 - 2023.md",
                "linksCollapsed": false,
                "unlinkedCollapsed": true
              }
            }
          },
          {
            "id": "87bb992dca14fffa",
            "type": "leaf",
            "state": {
              "type": "tag",
              "state": {
                "sortOrder": "frequency",
                "useHierarchy": true
              }
            }
          },
          {
            "id": "d82fbf37ee2686ec",
            "type": "leaf",
            "state": {
              "type": "outline",
              "state": {
                "file": "CalenderNotes/TOC/2023-10-03 Test ID - 36 Toc Test - 1 - 2023.md"
              }
            }
          },
          {
            "id": "ca7bc4254449ab06",
            "type": "leaf",
            "state": {
              "type": "git-view",
              "state": {}
            }
          },
          {
            "id": "07f63f9051c0c9ec",
            "type": "leaf",
            "state": {
              "type": "advanced-tables-toolbar",
              "state": {}
            }
          },
          {
            "id": "14ca28b6893474ae",
            "type": "leaf",
            "state": {
              "type": "all-properties",
              "state": {
                "sortOrder": "frequency"
              }
            }
          },
          {
            "id": "cb346972b2d728b3",
            "type": "leaf",
            "state": {
              "type": "full-calendar-sidebar-view",
              "state": {}
            }
          }
        ],
        "currentTab": 4
      }
    ],
    "direction": "horizontal",
    "width": 299.5
  },
  "left-ribbon": {
    "hiddenItems": {
      "switcher:Open quick switcher": false,
      "graph:Open graph view": false,
      "canvas:Create new canvas": false,
      "templates:Insert template": false,
      "command-palette:Open command palette": false,
      "random-note:Open random note": false,
      "audio-recorder:Start/stop recording": false,
      "daily-notes:Open today's daily note": false,
      "dbfolder:Create a new database table": false,
      "table-editor-obsidian:Advanced Tables Toolbar": false,
      "obsidian-full-calendar:Open Full Calendar": false,
      "obsidian-trash-explorer:Open trash explorer": false
    }
  },
  "active": "2949ed3f81e64650",
  "lastOpenFiles": [
    "CalenderNotes/TOC/media/Pasted image 20231005010755.png",
    "CalenderNotes/TOC/media",
    "CalenderNotes/TEST PROGRESS.md",
    "index.md",
    "DialyStuff/2023-10-05.md",
    "Refer UANOTES.md",
    "media/Pasted image 20231004231756.png",
    "media/Pasted image 20231004231708.png",
    "Revision/ZealRevision/DBMS/TRANSACTION-zeal.md",
    "Revision/ZealRevision/DBMS/media/Pasted image 20231004225626.png",
    "Test Canvas.canvas",
    "Revision/ZealRevision/DBMS/Untitled.md",
    "DialyStuff/2023-10-04.md",
    "Revision/Notes Revision/DLD/Flip Flops.md",
    "DaskBoard Back.md",
    "templates/dailyNote Template.md",
    "2023-10-04.md",
    "shortNotesList.md",
    "Revision/ZealRevision/ZealRevision.md",
    "Revision/ZealRevision/OS/OS-zeal.md",
    "Revision/ZealRevision/CN/CN.md",
    "Revision/ZealRevision/COA/COA-zeal.md",
    "Revision/ZealRevision/COA/Number Systems/Number System.md",
    "Revision/ZealRevision/ZealDB.md",
    "Revision/ZealRevision/DBMS/DBMS-zealwork.md",
    "Revision/ZealRevision/DBMS/Indexing DBMS ZEAL at 47.md",
    "Revision/ZealRevision/DBMS/media/Pasted image 20231004200211.png",
    "Revision/ZealRevision/DBMS/media/Pasted image 20231004200156.png",
    "Revision/ZealRevision/DBMS/media/Pasted image 20231004195905.png",
    "Revision/ZealRevision/DBMS/media/Pasted image 20231004160431.png",
    "Revision/ZealRevision/DBMS/media/Pasted image 20231004160119.png",
    "Revision/ZealRevision/DBMS/media/Pasted image 20231004155933.png",
    "Revision/ZealRevision/DBMS/media/Pasted image 20231004155914.png",
    "Revision/ZealRevision/DBMS/media",
    "CalenderNotes/2023-10-04 Test ID - 34 DBMS Test - 4 - 2023.md",
    "Revision/ZealRevision/DBMS",
    "TEST.md",
    "Untitled.md",
    "Revision/Revision.md",
    "Revision/PYQRevision/PYQ.md",
    "Revision/Notes Revision/DLD/media",
    "Revision/Notes Revision/DLD",
    "templates",
    "DialyStuff",
    "Revision/Notes Revision/Aptitude/Verbal/media",
    "Revision/Notes Revision/Aptitude/Non-verbal",
    "Revision/Notes Revision/Aptitude/Verbal",
    "Untitled 1.canvas"
  ]
}